cendat/CenDatHelper.py
cendat/CenDatResponse.py
cendat/__init__.py
cendat-0.8.1.dist-info/METADATA
cendat-0.8.1.dist-info/WHEEL
cendat-0.8.1.dist-info/licenses/LICENSE
cendat-0.8.1.dist-info/RECORD
