Metadata-Version: 2.4
Name: cendat
Version: 0.8.1
Summary: A helper library for exploring and fetching data from the U.S. Census Bureau API.
Project-URL: Homepage, https://github.com/mostlyunoriginal/cendat
Project-URL: Bug Tracker, https://github.com/mostlyunoriginal/cendat/issues
Author-email: "G. Lance Couzens" <lance.couzens@gmail.com>
License-File: LICENSE
Classifier: License :: OSI Approved :: MIT License
Classifier: Operating System :: OS Independent
Classifier: Programming Language :: Python :: 3
Requires-Python: >=3.9
Requires-Dist: requests
Provides-Extra: all
Requires-Dist: geopandas; extra == 'all'
Requires-Dist: pandas; extra == 'all'
Requires-Dist: polars; extra == 'all'
Provides-Extra: geopandas
Requires-Dist: geopandas; extra == 'geopandas'
Provides-Extra: pandas
Requires-Dist: pandas; extra == 'pandas'
Provides-Extra: polars
Requires-Dist: polars; extra == 'polars'
